{"1200": {"user_id": 8413357760, "user_msg_id": 1199}, "1205": {"user_id": 8413357760, "user_msg_id": 1204}, "1211": {"user_id": 7506502211, "user_msg_id": 1209}, "1212": {"user_id": 7506502211, "user_msg_id": 1210}, "1219": {"user_id": 8413357760, "user_msg_id": 1218}, "1223": {"user_id": 8413357760, "user_msg_id": 1222}, "1229": {"user_id": 8413357760, "user_msg_id": 1228}, "1230": {"user_id": 8413357760, "user_msg_id": 1228}, "1236": {"user_id": 8413357760, "user_msg_id": 1235}, "1237": {"user_id": 8413357760, "user_msg_id": 1235}, "1241": {"user_id": 8413357760, "user_msg_id": 1240}, "1242": {"user_id": 8413357760, "user_msg_id": 1240}, "1246": {"user_id": 8413357760, "user_msg_id": 1245}, "1247": {"user_id": 8413357760, "user_msg_id": 1245}, "1249": {"user_id": 8413357760, "user_msg_id": 1248}, "1250": {"user_id": 8413357760, "user_msg_id": 1248}, "1252": {"user_id": 7506502211, "user_msg_id": 1251}, "1253": {"user_id": 7506502211, "user_msg_id": 1251}, "1257": {"user_id": 7506502211, "user_msg_id": 1256}, "1258": {"user_id": 7506502211, "user_msg_id": 1256}, "1260": {"user_id": 7506502211, "user_msg_id": 1259}, "1261": {"user_id": 7506502211, "user_msg_id": 1259}, "1263": {"user_id": 7506502211, "user_msg_id": 1262}, "1264": {"user_id": 7506502211, "user_msg_id": 1262}, "1270": {"user_id": 8413357760, "user_msg_id": 1269}, "1271": {"user_id": 8413357760, "user_msg_id": 1269}, "1277": {"user_id": 7506502211, "user_msg_id": 1276}, "1278": {"user_id": 7506502211, "user_msg_id": 1276}, "1282": {"user_id": 7506502211, "user_msg_id": 1281}, "1288": {"user_id": 8413357760, "user_msg_id": 1287}, "1292": {"user_id": 8413357760, "user_msg_id": 1291}, "1296": {"user_id": 8413357760, "user_msg_id": 1295}, "1298": {"user_id": 7506502211, "user_msg_id": 1297}, "1300": {"user_id": 7506502211, "user_msg_id": 1299}, "1311": {"user_id": 8413357760, "user_msg_id": 1310}, "1313": {"user_id": 8413357760, "user_msg_id": 1312}, "1338": {"user_id": 8413357760, "user_msg_id": 1337}, "1340": {"user_id": 1069934362, "user_msg_id": 1339}, "1342": {"user_id": 1069934362, "user_msg_id": 1341}, "1349": {"user_id": 1069934362, "user_msg_id": 1348}, "1380": {"user_id": 8413357760, "user_msg_id": 1378}, "1385": {"user_id": 8413357760, "user_msg_id": 1383}, "1392": {"user_id": 8413357760, "user_msg_id": 1390}, "1396": {"user_id": 8413357760, "user_msg_id": 1395}, "1398": {"user_id": 8413357760, "user_msg_id": 1397}, "1401": {"user_id": 7010367159, "user_msg_id": 1400}}